druid_data/MockDynamo.py
druid_data/__init__.py
druid_data/main.py
druid_data-0.4.10.dist-info/LICENSE
druid_data-0.4.10.dist-info/METADATA
druid_data-0.4.10.dist-info/WHEEL
druid_data-0.4.10.dist-info/RECORD
