Metadata-Version: 2.1
Name: druid_data
Version: 0.4.10
Summary: A library to store and retrieve python objects in a DynamoDB database. It supports the basic CRUD operations
Home-page: https://github.com/druid-rio/druid-data
License: MIT
Keywords: Poetry,Virtual Environments,Tutorial,Packages,Packaging,Druid
Author: Druid
Maintainer: Fernando Magalhaes
Maintainer-email: fmagalhaes@druid.com.br
Requires-Python: >=3.11,<4.0
Classifier: License :: OSI Approved :: MIT License
Classifier: Programming Language :: Python :: 3
Classifier: Programming Language :: Python :: 3.11
Classifier: Programming Language :: Python :: 3.12
Requires-Dist: boto3 (>=1.35.0,<2.0.0)
Project-URL: Documentation, https://github.com/druid-rio/druid-data
Project-URL: Repository, https://github.com/druid-rio/druid-data.git
